testcontainers/redis/__init__.py
tests/test_redis.py
testcontainers_redis-0.0.1rc1.dist-info/METADATA
testcontainers_redis-0.0.1rc1.dist-info/WHEEL
testcontainers_redis-0.0.1rc1.dist-info/top_level.txt
testcontainers_redis-0.0.1rc1.dist-info/RECORD
